TornAPIWrapper/__init__.py
TornAPIWrapper/__main__.py
TornAPIWrapper/errors.py
TornAPIWrapper/faction.py
TornAPIWrapper/forum.py
TornAPIWrapper/key.py
TornAPIWrapper/market.py
TornAPIWrapper/property.py
TornAPIWrapper/racing.py
TornAPIWrapper/torn.py
TornAPIWrapper/torn_api_wrapper.py
TornAPIWrapper/type_hints.py
TornAPIWrapper/user.py
tornapiwrapper-2.0.1.dist-info/licenses/LICENSE
tornapiwrapper-2.0.1.dist-info/METADATA
tornapiwrapper-2.0.1.dist-info/WHEEL
tornapiwrapper-2.0.1.dist-info/top_level.txt
tornapiwrapper-2.0.1.dist-info/RECORD
