Metadata-Version: 2.4
Name: TornAPIWrapper
Version: 2.0.1
Summary: A Python wrapper for the Torn City API, providing access to Torn City data.
Author: cxdzc
License: The MIT License (MIT)
Project-URL: Homepage, https://github.com/cxdzc/TornAPIWrapper
Project-URL: Repository, https://github.com/cxdzc/TornAPIWrapper
Project-URL: Issues, https://github.com/cxdzc/TornAPIWrapper/issues
Keywords: torn,torn-city,torn-city-api,torncom,wrapper,api,python
Classifier: Programming Language :: Python :: 3.13
Classifier: Programming Language :: Python :: 3.14
Classifier: Programming Language :: Python :: 3.15
Classifier: License :: OSI Approved :: MIT License
Classifier: Operating System :: OS Independent
Classifier: Topic :: Internet
Classifier: Topic :: Software Development :: Libraries
Classifier: Topic :: Software Development :: Libraries :: Python Modules
Classifier: Topic :: Utilities
Classifier: Natural Language :: English
Requires-Python: >=3.13
License-File: LICENSE
Requires-Dist: requests
Dynamic: license-file
